ddhi_aggregator/__init__.py
ddhi_aggregator/aggregate.py
ddhi_aggregator/aggregators/aggregators.py
ddhi_aggregator/entities/entities.py
ddhi_aggregator/transformer/transformer.py
xsl/__init__.py
xsl/ddhi-tei2repo.xsl
ddhi_aggregator-1.1.0.dist-info/AUTHORS.rst
ddhi_aggregator-1.1.0.dist-info/LICENSE.txt
ddhi_aggregator-1.1.0.dist-info/METADATA
ddhi_aggregator-1.1.0.dist-info/WHEEL
ddhi_aggregator-1.1.0.dist-info/entry_points.txt
ddhi_aggregator-1.1.0.dist-info/top_level.txt
ddhi_aggregator-1.1.0.dist-info/RECORD
