Metadata-Version: 2.1
Name: ddhi-aggregator
Version: 1.1.0
Summary: Aggregator for DDHI
Home-page: https://github.com/pyscaffold/pyscaffold/
Author: Cliff Wulfman
Author-email: cliff@agilehumanities.ca
License: mit
Project-URL: Documentation, https://agilehumanities.ca
Platform: any
Classifier: Development Status :: 4 - Beta
Classifier: Programming Language :: Python
Requires-Python: >=3.7
License-File: LICENSE.txt
License-File: AUTHORS.rst
Requires-Dist: lxml
Requires-Dist: ddhi-encoder
Provides-Extra: testing
Requires-Dist: pytest ; extra == 'testing'
Requires-Dist: pytest-cov ; extra == 'testing'
